gstlearn/__init__.py
gstlearn/_gstlearn.so
gstlearn/conv.py
gstlearn/document.py
gstlearn/gstmarimo.py
gstlearn/plot.py
gstlearn/plot3D.py
gstlearn/proj.py
gstlearn/segy.py
gstlearn/test.py
gstlearn/version.py
gstlearn/widgets.py
gstlearn-1.10.1.dist-info/licenses/LICENSE
gstlearn-1.10.1.dist-info/METADATA
gstlearn-1.10.1.dist-info/WHEEL
gstlearn-1.10.1.dist-info/top_level.txt
gstlearn-1.10.1.dist-info/RECORD
