Metadata-Version: 2.4
Name: gstlearn
Version: 1.10.1
Summary: Geostatistics & Machine Learning toolbox
Author-email: Team gstlearn <gstlearn@groupes.mines-paristech.fr>
License-Expression: BSD-3-Clause
Project-URL: Homepage, https://gstlearn.org
Project-URL: Issues, https://gstlearn.org/?page_id=468
Platform: Windows
Platform: Linux
Platform: Mac OS-X
Classifier: Programming Language :: Python :: 3
Classifier: Programming Language :: C++
Classifier: Development Status :: 4 - Beta
Classifier: Environment :: Other Environment
Classifier: Intended Audience :: Developers
Classifier: Operating System :: OS Independent
Classifier: Topic :: Software Development :: Libraries :: Python Modules
Requires-Python: >=3.8
License-File: LICENSE
Requires-Dist: numpy<3,>=1.24
Provides-Extra: plot
Requires-Dist: matplotlib; extra == "plot"
Requires-Dist: plotly; extra == "plot"
Requires-Dist: pyproj; extra == "plot"
Provides-Extra: conv
Requires-Dist: pandas; extra == "conv"
Requires-Dist: scipy; extra == "conv"
Provides-Extra: doc
Requires-Dist: requests; extra == "doc"
Requires-Dist: IPython; extra == "doc"
Provides-Extra: all
Requires-Dist: gstlearn[conv,doc,plot]; extra == "all"
Provides-Extra: marimo
Requires-Dist: gstlearn[all]; extra == "marimo"
Requires-Dist: marimo[recommended]; extra == "marimo"
Requires-Dist: contextily; extra == "marimo"
Dynamic: license-file
